evalAIRR/__init__.py
evalAIRR/main.py
evalAIRR/version.py
evalAIRR/util/__init__.py
evalAIRR/util/copula.py
evalAIRR/util/corr.py
evalAIRR/util/input.py
evalAIRR/util/ml.py
evalAIRR/util/pca.py
evalAIRR/util/report.py
evalAIRR/util/univar.py
evalAIRR-0.0.44.dist-info/METADATA
evalAIRR-0.0.44.dist-info/WHEEL
evalAIRR-0.0.44.dist-info/entry_points.txt
evalAIRR-0.0.44.dist-info/top_level.txt
evalAIRR-0.0.44.dist-info/RECORD
