Metadata-Version: 2.1
Name: evalAIRR
Version: 0.0.44
Summary: Comparison of real and simulated AIRR datasets
Author: Lukas Sparnauskas
Author-email: <lukas.11sp@gmail.com>
License: MIT
Keywords: python,airr,simulated data,ml,machine learning
Classifier: Development Status :: 2 - Pre-Alpha
Classifier: Intended Audience :: Science/Research
Classifier: Programming Language :: Python :: 3
Classifier: Programming Language :: Python :: 3.8
Classifier: Programming Language :: Python :: 3.10
Classifier: Environment :: Console
Classifier: Operating System :: Unix
Classifier: Operating System :: MacOS :: MacOS X
Classifier: Operating System :: Microsoft :: Windows
